{
  "config": "{\"version\":\"5.54\",\"themeCollection\":{\"baseTheme\":{\"name\":\"CY24SU02\",\"version\":\"5.52\",\"type\":2}},\"activeSectionIndex\":0,\"defaultDrillFilterOtherVisuals\":true,\"linguisticSchemaSyncVersion\":2,\"settings\":{\"useNewFilterPaneExperience\":true,\"allowChangeFilterTypes\":true,\"useStylableVisualContainerHeader\":true,\"queryLimitOption\":6,\"exportDataMode\":1,\"useDefaultAggregateDisplayName\":true,\"useEnhancedTooltips\":true},\"objects\":{\"section\":[{\"properties\":{\"verticalAlignment\":{\"expr\":{\"Literal\":{\"Value\":\"'Top'\"}}}}}],\"outspacePane\":[{\"properties\":{\"expanded\":{\"expr\":{\"Literal\":{\"Value\":\"false\"}}}}}]}}",
  "layoutOptimization": 0,
  "resourcePackages": [
    {
      "resourcePackage": {
        "disabled": false,
        "items": [
          {
            "name": "CY24SU02",
            "path": "BaseThemes/CY24SU02.json",
            "type": 202
          }
        ],
        "name": "SharedResources",
        "type": 2
      }
    },
    {
      "resourcePackage": {
        "disabled": false,
        "items": [
          {
            "name": "Day_02_Logistics_-_Background8123095895108554.png",
            "path": "Day_02_Logistics_-_Background8123095895108554.png",
            "type": 100
          }
        ],
        "name": "RegisteredResources",
        "type": 1
      }
    }
  ],
  "sections": [
    {
      "config": "{\"objects\":{\"background\":[{\"properties\":{\"image\":{\"image\":{\"name\":{\"expr\":{\"Literal\":{\"Value\":\"'Day 02 Logistics - Background.png'\"}}},\"url\":{\"expr\":{\"ResourcePackageItem\":{\"PackageName\":\"RegisteredResources\",\"PackageType\":1,\"ItemName\":\"Day_02_Logistics_-_Background8123095895108554.png\"}}},\"scaling\":{\"expr\":{\"Literal\":{\"Value\":\"'Normal'\"}}}}},\"transparency\":{\"expr\":{\"Literal\":{\"Value\":\"0D\"}}}}}]}}",
      "displayName": "Page 1",
      "displayOption": 1,
      "filters": "[]",
      "height": 720.00,
      "name": "ReportSection",
      "visualContainers": [
        {
          "config": "{\"name\":\"1db405c37723a4bad501\",\"layouts\":[{\"id\":0,\"position\":{\"x\":66.0036832412523,\"y\":215.69060773480663,\"z\":4000,\"width\":398.37937384898714,\"height\":201.54696132596686,\"tabOrder\":4000}}],\"singleVisual\":{\"visualType\":\"columnChart\",\"projections\":{\"Y\":[{\"queryRef\":\"0-Measures.Count of Orders\"}],\"Category\":[{\"queryRef\":\"factInvoices.Invoicing Date.Variation.Date Hierarchy.Month\",\"active\":true}],\"Series\":[{\"queryRef\":\"factInvoices.Status\"}]},\"prototypeQuery\":{\"Version\":2,\"From\":[{\"Name\":\"0\",\"Entity\":\"0-Measures\",\"Type\":0},{\"Name\":\"f\",\"Entity\":\"factInvoices\",\"Type\":0}],\"Select\":[{\"Measure\":{\"Expression\":{\"SourceRef\":{\"Source\":\"0\"}},\"Property\":\"Count of Orders\"},\"Name\":\"0-Measures.Count of Orders\",\"NativeReferenceName\":\"Count of Orders\"},{\"HierarchyLevel\":{\"Expression\":{\"Hierarchy\":{\"Expression\":{\"PropertyVariationSource\":{\"Expression\":{\"SourceRef\":{\"Source\":\"f\"}},\"Name\":\"Variation\",\"Property\":\"Invoicing Date\"}},\"Hierarchy\":\"Date Hierarchy\"}},\"Level\":\"Month\"},\"Name\":\"factInvoices.Invoicing Date.Variation.Date Hierarchy.Month\",\"NativeReferenceName\":\"Invoicing Date Month\"},{\"Column\":{\"Expression\":{\"SourceRef\":{\"Source\":\"f\"}},\"Property\":\"Status\"},\"Name\":\"factInvoices.Status\",\"NativeReferenceName\":\"Status\"}]},\"drillFilterOtherVisuals\":true,\"objects\":{\"categoryAxis\":[{\"properties\":{\"show\":{\"expr\":{\"Literal\":{\"Value\":\"true\"}}},\"showAxisTitle\":{\"expr\":{\"Literal\":{\"Value\":\"false\"}}}}}],\"valueAxis\":[{\"properties\":{\"show\":{\"expr\":{\"Literal\":{\"Value\":\"false\"}}},\"showAxisTitle\":{\"expr\":{\"Literal\":{\"Value\":\"false\"}}}}}],\"legend\":[{\"properties\":{\"position\":{\"expr\":{\"Literal\":{\"Value\":\"'TopCenter'\"}}},\"showTitle\":{\"expr\":{\"Literal\":{\"Value\":\"false\"}}}}}],\"labels\":[{\"properties\":{\"show\":{\"expr\":{\"Literal\":{\"Value\":\"true\"}}}}}],\"totals\":[{\"properties\":{\"show\":{\"expr\":{\"Literal\":{\"Value\":\"true\"}}}}}]},\"vcObjects\":{\"background\":[{\"properties\":{\"show\":{\"expr\":{\"Literal\":{\"Value\":\"false\"}}}}}],\"title\":[{\"properties\":{\"text\":{\"expr\":{\"Literal\":{\"Value\":\"'Orders by Month and Status'\"}}},\"show\":{\"expr\":{\"Literal\":{\"Value\":\"true\"}}}}}],\"visualHeader\":[{\"properties\":{\"show\":{\"expr\":{\"Literal\":{\"Value\":\"false\"}}}}}]}}}",
          "filters": "[]",
          "height": 201.55,
          "width": 398.38,
          "x": 66.00,
          "y": 215.69,
          "z": 4000.00
        },
        {
          "config": "{\"name\":\"4e1668430ab74251509e\",\"layouts\":[{\"id\":0,\"position\":{\"x\":128.11337466784764,\"y\":136.04960141718334,\"z\":5000,\"width\":122.444641275465,\"height\":55.55358724534987,\"tabOrder\":5000}}],\"singleVisual\":{\"visualType\":\"card\",\"projections\":{\"Values\":[{\"queryRef\":\"0-Measures.Count of Orders\"}]},\"prototypeQuery\":{\"Version\":2,\"From\":[{\"Name\":\"0\",\"Entity\":\"0-Measures\",\"Type\":0}],\"Select\":[{\"Measure\":{\"Expression\":{\"SourceRef\":{\"Source\":\"0\"}},\"Property\":\"Count of Orders\"},\"Name\":\"0-Measures.Count of Orders\",\"NativeReferenceName\":\"Count of Orders\"}],\"OrderBy\":[{\"Direction\":2,\"Expression\":{\"Measure\":{\"Expression\":{\"SourceRef\":{\"Source\":\"0\"}},\"Property\":\"Count of Orders\"}}}]},\"drillFilterOtherVisuals\":true,\"hasDefaultSort\":true,\"objects\":{\"labels\":[{\"properties\":{\"fontSize\":{\"expr\":{\"Literal\":{\"Value\":\"25D\"}}}}}],\"categoryLabels\":[{\"properties\":{\"show\":{\"expr\":{\"Literal\":{\"Value\":\"false\"}}}}}]},\"vcObjects\":{\"background\":[{\"properties\":{\"show\":{\"expr\":{\"Literal\":{\"Value\":\"false\"}}}}}]}}}",
          "filters": "[]",
          "height": 55.55,
          "width": 122.44,
          "x": 128.11,
          "y": 136.05,
          "z": 5000.00
        },
        {
          "config": "{\"name\":\"71dc4779916e04a9158c\",\"layouts\":[{\"id\":0,\"position\":{\"x\":480.8839779005525,\"y\":427.84530386740335,\"z\":0,\"width\":381.8784530386741,\"height\":207.4401473296501,\"tabOrder\":0}}],\"singleVisual\":{\"visualType\":\"clusteredBarChart\",\"projections\":{\"Y\":[{\"queryRef\":\"0-Measures.OTIF\"}],\"Category\":[{\"queryRef\":\"dimCarrier.Carrier\",\"active\":true}]},\"prototypeQuery\":{\"Version\":2,\"From\":[{\"Name\":\"0\",\"Entity\":\"0-Measures\",\"Type\":0},{\"Name\":\"d\",\"Entity\":\"dimCarrier\",\"Type\":0}],\"Select\":[{\"Measure\":{\"Expression\":{\"SourceRef\":{\"Source\":\"0\"}},\"Property\":\"OTIF\"},\"Name\":\"0-Measures.OTIF\",\"NativeReferenceName\":\"OTIF\"},{\"Column\":{\"Expression\":{\"SourceRef\":{\"Source\":\"d\"}},\"Property\":\"Carrier\"},\"Name\":\"dimCarrier.Carrier\",\"NativeReferenceName\":\"Carrier\"}],\"OrderBy\":[{\"Direction\":2,\"Expression\":{\"Measure\":{\"Expression\":{\"SourceRef\":{\"Source\":\"0\"}},\"Property\":\"OTIF\"}}}]},\"drillFilterOtherVisuals\":true,\"hasDefaultSort\":true,\"objects\":{\"legend\":[{\"properties\":{\"position\":{\"expr\":{\"Literal\":{\"Value\":\"'TopCenter'\"}}},\"showTitle\":{\"expr\":{\"Literal\":{\"Value\":\"false\"}}}}}],\"labels\":[{\"properties\":{\"show\":{\"expr\":{\"Literal\":{\"Value\":\"true\"}}}}}],\"categoryAxis\":[{\"properties\":{\"showAxisTitle\":{\"expr\":{\"Literal\":{\"Value\":\"false\"}}}}}],\"valueAxis\":[{\"properties\":{\"showAxisTitle\":{\"expr\":{\"Literal\":{\"Value\":\"false\"}}}}}]},\"vcObjects\":{\"title\":[{\"properties\":{\"titleWrap\":{\"expr\":{\"Literal\":{\"Value\":\"true\"}}}}}],\"background\":[{\"properties\":{\"show\":{\"expr\":{\"Literal\":{\"Value\":\"false\"}}},\"transparency\":{\"expr\":{\"Literal\":{\"Value\":\"0D\"}}}}}]}}}",
          "filters": "[]",
          "height": 207.44,
          "width": 381.88,
          "x": 480.88,
          "y": 427.85,
          "z": 0.00
        },
        {
          "config": "{\"name\":\"726076a0a0598a1547c7\",\"layouts\":[{\"id\":0,\"position\":{\"x\":342.39149689991143,\"y\":136.04960141718334,\"z\":6000,\"width\":122.444641275465,\"height\":55.55358724534987,\"tabOrder\":6000}}],\"singleVisual\":{\"visualType\":\"card\",\"projections\":{\"Values\":[{\"queryRef\":\"Sum(factInvoices.Invoice Value)\"}]},\"prototypeQuery\":{\"Version\":2,\"From\":[{\"Name\":\"f\",\"Entity\":\"factInvoices\",\"Type\":0}],\"Select\":[{\"Aggregation\":{\"Expression\":{\"Column\":{\"Expression\":{\"SourceRef\":{\"Source\":\"f\"}},\"Property\":\"Invoice Value\"}},\"Function\":0},\"Name\":\"Sum(factInvoices.Invoice Value)\",\"NativeReferenceName\":\"Sum of Invoice Value\"}],\"OrderBy\":[{\"Direction\":2,\"Expression\":{\"Aggregation\":{\"Expression\":{\"Column\":{\"Expression\":{\"SourceRef\":{\"Source\":\"f\"}},\"Property\":\"Invoice Value\"}},\"Function\":0}}}]},\"drillFilterOtherVisuals\":true,\"hasDefaultSort\":true,\"objects\":{\"labels\":[{\"properties\":{\"fontSize\":{\"expr\":{\"Literal\":{\"Value\":\"25D\"}}}}}],\"categoryLabels\":[{\"properties\":{\"show\":{\"expr\":{\"Literal\":{\"Value\":\"false\"}}}}}]},\"vcObjects\":{\"background\":[{\"properties\":{\"show\":{\"expr\":{\"Literal\":{\"Value\":\"false\"}}}}}]}}}",
          "filters": "[]",
          "height": 55.55,
          "width": 122.44,
          "x": 342.39,
          "y": 136.05,
          "z": 6000.00
        },
        {
          "config": "{\"name\":\"76ce61749a5d214bd75b\",\"layouts\":[{\"id\":0,\"position\":{\"x\":480.8839779005525,\"y\":215.69060773480663,\"z\":1000,\"width\":381.8784530386741,\"height\":201.54696132596686,\"tabOrder\":1000}}],\"singleVisual\":{\"visualType\":\"clusteredBarChart\",\"projections\":{\"Y\":[{\"queryRef\":\"0-Measures.OTIF\"}],\"Category\":[{\"queryRef\":\"dimClient.ClientName\",\"active\":true}]},\"prototypeQuery\":{\"Version\":2,\"From\":[{\"Name\":\"0\",\"Entity\":\"0-Measures\",\"Type\":0},{\"Name\":\"d\",\"Entity\":\"dimClient\",\"Type\":0}],\"Select\":[{\"Measure\":{\"Expression\":{\"SourceRef\":{\"Source\":\"0\"}},\"Property\":\"OTIF\"},\"Name\":\"0-Measures.OTIF\",\"NativeReferenceName\":\"OTIF\"},{\"Column\":{\"Expression\":{\"SourceRef\":{\"Source\":\"d\"}},\"Property\":\"ClientName\"},\"Name\":\"dimClient.ClientName\",\"NativeReferenceName\":\"ClientName\"}],\"OrderBy\":[{\"Direction\":2,\"Expression\":{\"Measure\":{\"Expression\":{\"SourceRef\":{\"Source\":\"0\"}},\"Property\":\"OTIF\"}}}]},\"drillFilterOtherVisuals\":true,\"hasDefaultSort\":true,\"objects\":{\"legend\":[{\"properties\":{\"position\":{\"expr\":{\"Literal\":{\"Value\":\"'TopCenter'\"}}},\"showTitle\":{\"expr\":{\"Literal\":{\"Value\":\"false\"}}}}}],\"categoryAxis\":[{\"properties\":{\"show\":{\"expr\":{\"Literal\":{\"Value\":\"true\"}}},\"showAxisTitle\":{\"expr\":{\"Literal\":{\"Value\":\"false\"}}}}}],\"valueAxis\":[{\"properties\":{\"show\":{\"expr\":{\"Literal\":{\"Value\":\"false\"}}},\"showAxisTitle\":{\"expr\":{\"Literal\":{\"Value\":\"false\"}}}}}],\"labels\":[{\"properties\":{\"show\":{\"expr\":{\"Literal\":{\"Value\":\"true\"}}}}}]},\"vcObjects\":{\"title\":[{\"properties\":{\"titleWrap\":{\"expr\":{\"Literal\":{\"Value\":\"true\"}}},\"text\":{\"expr\":{\"Literal\":{\"Value\":\"'Buttom 5 Client by OTIF'\"}}}}}],\"background\":[{\"properties\":{\"show\":{\"expr\":{\"Literal\":{\"Value\":\"false\"}}},\"transparency\":{\"expr\":{\"Literal\":{\"Value\":\"0D\"}}}}}]}}}",
          "filters": "[{\"expression\":{\"Column\":{\"Expression\":{\"SourceRef\":{\"Entity\":\"dimClient\"}},\"Property\":\"ClientName\"}},\"filter\":{\"Version\":2,\"From\":[{\"Name\":\"subquery\",\"Expression\":{\"Subquery\":{\"Query\":{\"Version\":2,\"From\":[{\"Name\":\"0\",\"Entity\":\"0-Measures\",\"Type\":0},{\"Name\":\"d\",\"Entity\":\"dimClient\",\"Type\":0}],\"Select\":[{\"Column\":{\"Expression\":{\"SourceRef\":{\"Source\":\"d\"}},\"Property\":\"ClientName\"},\"Name\":\"field\"}],\"OrderBy\":[{\"Direction\":1,\"Expression\":{\"Measure\":{\"Expression\":{\"SourceRef\":{\"Source\":\"0\"}},\"Property\":\"OTIF\"}}}],\"Top\":5}}},\"Type\":2},{\"Name\":\"d\",\"Entity\":\"dimClient\",\"Type\":0}],\"Where\":[{\"Condition\":{\"In\":{\"Expressions\":[{\"Column\":{\"Expression\":{\"SourceRef\":{\"Source\":\"d\"}},\"Property\":\"ClientName\"}}],\"Table\":{\"SourceRef\":{\"Source\":\"subquery\"}}}}}]},\"type\":\"TopN\",\"howCreated\":0,\"isHiddenInViewMode\":false}]",
          "height": 201.55,
          "width": 381.88,
          "x": 480.88,
          "y": 215.69,
          "z": 1000.00
        },
        {
          "config": "{\"name\":\"7fdb25132c181aa3ae49\",\"layouts\":[{\"id\":0,\"position\":{\"x\":213.33333333333334,\"y\":486.77716390423575,\"z\":9000,\"width\":96.64825046040517,\"height\":88.39779005524862,\"tabOrder\":9000}}],\"singleVisual\":{\"visualType\":\"card\",\"projections\":{\"Values\":[{\"queryRef\":\"0-Measures.OTIF\"}]},\"prototypeQuery\":{\"Version\":2,\"From\":[{\"Name\":\"0\",\"Entity\":\"0-Measures\",\"Type\":0}],\"Select\":[{\"Measure\":{\"Expression\":{\"SourceRef\":{\"Source\":\"0\"}},\"Property\":\"OTIF\"},\"Name\":\"0-Measures.OTIF\",\"NativeReferenceName\":\"OTIF\"}],\"OrderBy\":[{\"Direction\":2,\"Expression\":{\"Measure\":{\"Expression\":{\"SourceRef\":{\"Source\":\"0\"}},\"Property\":\"OTIF\"}}}]},\"drillFilterOtherVisuals\":true,\"hasDefaultSort\":true,\"objects\":{\"labels\":[{\"properties\":{\"fontSize\":{\"expr\":{\"Literal\":{\"Value\":\"15D\"}}},\"bold\":{\"expr\":{\"Literal\":{\"Value\":\"true\"}}}}}],\"categoryLabels\":[{\"properties\":{\"show\":{\"expr\":{\"Literal\":{\"Value\":\"true\"}}}}}]},\"vcObjects\":{\"title\":[{\"properties\":{\"titleWrap\":{\"expr\":{\"Literal\":{\"Value\":\"true\"}}}}}],\"background\":[{\"properties\":{\"show\":{\"expr\":{\"Literal\":{\"Value\":\"false\"}}},\"transparency\":{\"expr\":{\"Literal\":{\"Value\":\"0D\"}}}}}]}}}",
          "filters": "[]",
          "height": 88.40,
          "width": 96.65,
          "x": 213.33,
          "y": 486.78,
          "z": 9000.00
        },
        {
          "config": "{\"name\":\"9538f2e17360050ab616\",\"layouts\":[{\"id\":0,\"position\":{\"x\":66.0036832412523,\"y\":427.84530386740335,\"z\":3000,\"width\":398.37937384898714,\"height\":207.4401473296501,\"tabOrder\":3000}}],\"singleVisual\":{\"visualType\":\"donutChart\",\"projections\":{\"Y\":[{\"queryRef\":\"0-Measures.OTIF\"},{\"queryRef\":\"0-Measures.NotOTIF\"}]},\"prototypeQuery\":{\"Version\":2,\"From\":[{\"Name\":\"0\",\"Entity\":\"0-Measures\",\"Type\":0}],\"Select\":[{\"Measure\":{\"Expression\":{\"SourceRef\":{\"Source\":\"0\"}},\"Property\":\"OTIF\"},\"Name\":\"0-Measures.OTIF\",\"NativeReferenceName\":\"OTIF\"},{\"Measure\":{\"Expression\":{\"SourceRef\":{\"Source\":\"0\"}},\"Property\":\"NotOTIF\"},\"Name\":\"0-Measures.NotOTIF\",\"NativeReferenceName\":\"NotOTIF\"}],\"OrderBy\":[{\"Direction\":2,\"Expression\":{\"Measure\":{\"Expression\":{\"SourceRef\":{\"Source\":\"0\"}},\"Property\":\"OTIF\"}}}]},\"drillFilterOtherVisuals\":true,\"hasDefaultSort\":true,\"objects\":{\"legend\":[{\"properties\":{\"position\":{\"expr\":{\"Literal\":{\"Value\":\"'TopCenter'\"}}},\"showTitle\":{\"expr\":{\"Literal\":{\"Value\":\"false\"}}},\"show\":{\"expr\":{\"Literal\":{\"Value\":\"false\"}}}}}],\"labels\":[{\"properties\":{\"show\":{\"expr\":{\"Literal\":{\"Value\":\"true\"}}},\"labelStyle\":{\"expr\":{\"Literal\":{\"Value\":\"'Percent of total'\"}}},\"position\":{\"expr\":{\"Literal\":{\"Value\":\"'outside'\"}}}}}],\"slices\":[{\"properties\":{\"innerRadiusRatio\":{\"expr\":{\"Literal\":{\"Value\":\"83L\"}}}}}],\"dataPoint\":[{\"properties\":{\"fill\":{\"solid\":{\"color\":{\"expr\":{\"ThemeDataColor\":{\"ColorId\":4,\"Percent\":-0.5}}}}}},\"selector\":{\"metadata\":\"0-Measures.NotOTIF\"}},{\"properties\":{\"fill\":{\"solid\":{\"color\":{\"expr\":{\"Literal\":{\"Value\":\"'#00F815'\"}}}}}},\"selector\":{\"metadata\":\"0-Measures.OTIF\"}}]},\"vcObjects\":{\"title\":[{\"properties\":{\"titleWrap\":{\"expr\":{\"Literal\":{\"Value\":\"true\"}}},\"show\":{\"expr\":{\"Literal\":{\"Value\":\"false\"}}}}}],\"background\":[{\"properties\":{\"show\":{\"expr\":{\"Literal\":{\"Value\":\"false\"}}},\"transparency\":{\"expr\":{\"Literal\":{\"Value\":\"0D\"}}}}}]}}}",
          "filters": "[]",
          "height": 207.44,
          "width": 398.38,
          "x": 66.00,
          "y": 427.85,
          "z": 3000.00
        },
        {
          "config": "{\"name\":\"b67b83924698da0b6de2\",\"layouts\":[{\"id\":0,\"position\":{\"x\":538.5296722763508,\"y\":136.04960141718334,\"z\":7000,\"width\":122.444641275465,\"height\":55.55358724534987,\"tabOrder\":7000}}],\"singleVisual\":{\"visualType\":\"card\",\"projections\":{\"Values\":[{\"queryRef\":\"Sum(factInvoices.Number of Packages)\"}]},\"prototypeQuery\":{\"Version\":2,\"From\":[{\"Name\":\"f\",\"Entity\":\"factInvoices\",\"Type\":0}],\"Select\":[{\"Aggregation\":{\"Expression\":{\"Column\":{\"Expression\":{\"SourceRef\":{\"Source\":\"f\"}},\"Property\":\"Number of Packages\"}},\"Function\":0},\"Name\":\"Sum(factInvoices.Number of Packages)\",\"NativeReferenceName\":\"Sum of Number of Packages\"}],\"OrderBy\":[{\"Direction\":2,\"Expression\":{\"Aggregation\":{\"Expression\":{\"Column\":{\"Expression\":{\"SourceRef\":{\"Source\":\"f\"}},\"Property\":\"Number of Packages\"}},\"Function\":0}}}]},\"drillFilterOtherVisuals\":true,\"hasDefaultSort\":true,\"objects\":{\"labels\":[{\"properties\":{\"fontSize\":{\"expr\":{\"Literal\":{\"Value\":\"25D\"}}}}}],\"categoryLabels\":[{\"properties\":{\"show\":{\"expr\":{\"Literal\":{\"Value\":\"false\"}}}}}]},\"vcObjects\":{\"background\":[{\"properties\":{\"show\":{\"expr\":{\"Literal\":{\"Value\":\"false\"}}}}}]}}}",
          "filters": "[]",
          "height": 55.55,
          "width": 122.44,
          "x": 538.53,
          "y": 136.05,
          "z": 7000.00
        },
        {
          "config": "{\"name\":\"c3990c4563c1284cd161\",\"layouts\":[{\"id\":0,\"position\":{\"x\":740.3365810451727,\"y\":136.04960141718334,\"z\":8000,\"width\":122.444641275465,\"height\":55.55358724534987,\"tabOrder\":8000}}],\"singleVisual\":{\"visualType\":\"card\",\"projections\":{\"Values\":[{\"queryRef\":\"Sum(factInvoices.Gross Weight (kg))\"}]},\"prototypeQuery\":{\"Version\":2,\"From\":[{\"Name\":\"f\",\"Entity\":\"factInvoices\",\"Type\":0}],\"Select\":[{\"Aggregation\":{\"Expression\":{\"Column\":{\"Expression\":{\"SourceRef\":{\"Source\":\"f\"}},\"Property\":\"Gross Weight (kg)\"}},\"Function\":0},\"Name\":\"Sum(factInvoices.Gross Weight (kg))\",\"NativeReferenceName\":\"Sum of Gross Weight (kg)\"}],\"OrderBy\":[{\"Direction\":2,\"Expression\":{\"Aggregation\":{\"Expression\":{\"Column\":{\"Expression\":{\"SourceRef\":{\"Source\":\"f\"}},\"Property\":\"Gross Weight (kg)\"}},\"Function\":0}}}]},\"drillFilterOtherVisuals\":true,\"hasDefaultSort\":true,\"objects\":{\"labels\":[{\"properties\":{\"fontSize\":{\"expr\":{\"Literal\":{\"Value\":\"25D\"}}}}}],\"categoryLabels\":[{\"properties\":{\"show\":{\"expr\":{\"Literal\":{\"Value\":\"false\"}}}}}]},\"vcObjects\":{\"background\":[{\"properties\":{\"show\":{\"expr\":{\"Literal\":{\"Value\":\"false\"}}}}}]}}}",
          "filters": "[]",
          "height": 55.55,
          "width": 122.44,
          "x": 740.34,
          "y": 136.05,
          "z": 8000.00
        },
        {
          "config": "{\"name\":\"d7e5227957ee4745207c\",\"layouts\":[{\"id\":0,\"position\":{\"x\":889.8710865561695,\"y\":129.65009208103132,\"z\":2000,\"width\":345.340699815838,\"height\":505.63535911602213,\"tabOrder\":2000}}],\"singleVisual\":{\"visualType\":\"map\",\"projections\":{\"Category\":[{\"queryRef\":\"factInvoices.Origin City\",\"active\":true}],\"Size\":[{\"queryRef\":\"CountNonNull(factInvoices.Status)\"}],\"Series\":[{\"queryRef\":\"dimClient.Country\"}]},\"prototypeQuery\":{\"Version\":2,\"From\":[{\"Name\":\"f\",\"Entity\":\"factInvoices\",\"Type\":0},{\"Name\":\"d\",\"Entity\":\"dimClient\",\"Type\":0}],\"Select\":[{\"Column\":{\"Expression\":{\"SourceRef\":{\"Source\":\"f\"}},\"Property\":\"Origin City\"},\"Name\":\"factInvoices.Origin City\",\"NativeReferenceName\":\"Origin City\"},{\"Aggregation\":{\"Expression\":{\"Column\":{\"Expression\":{\"SourceRef\":{\"Source\":\"f\"}},\"Property\":\"Status\"}},\"Function\":5},\"Name\":\"CountNonNull(factInvoices.Status)\",\"NativeReferenceName\":\"Count of Status\"},{\"Column\":{\"Expression\":{\"SourceRef\":{\"Source\":\"d\"}},\"Property\":\"Country\"},\"Name\":\"dimClient.Country\",\"NativeReferenceName\":\"Country\"}]},\"drillFilterOtherVisuals\":true,\"filterSortOrder\":3,\"objects\":{\"legend\":[{\"properties\":{\"position\":{\"expr\":{\"Literal\":{\"Value\":\"'TopCenter'\"}}},\"showTitle\":{\"expr\":{\"Literal\":{\"Value\":\"false\"}}},\"show\":{\"expr\":{\"Literal\":{\"Value\":\"true\"}}}}}],\"mapStyles\":[{\"properties\":{\"mapTheme\":{\"expr\":{\"Literal\":{\"Value\":\"'road'\"}}}}}]},\"vcObjects\":{\"title\":[{\"properties\":{\"titleWrap\":{\"expr\":{\"Literal\":{\"Value\":\"true\"}}},\"show\":{\"expr\":{\"Literal\":{\"Value\":\"true\"}}},\"text\":{\"expr\":{\"Literal\":{\"Value\":\"'Origin of Late Deliveries'\"}}}}}],\"background\":[{\"properties\":{\"show\":{\"expr\":{\"Literal\":{\"Value\":\"false\"}}},\"transparency\":{\"expr\":{\"Literal\":{\"Value\":\"0D\"}}}}}]}}}",
          "filters": "[{\"name\":\"Filter7d5c89b562758152749e\",\"expression\":{\"Aggregation\":{\"Expression\":{\"Column\":{\"Expression\":{\"SourceRef\":{\"Entity\":\"factInvoices\"}},\"Property\":\"Status\"}},\"Function\":5}},\"type\":\"Advanced\",\"howCreated\":0,\"isHiddenInViewMode\":false,\"ordinal\":0},{\"name\":\"Filterfaa1876700b3d8b326d1\",\"expression\":{\"Column\":{\"Expression\":{\"SourceRef\":{\"Entity\":\"factInvoices\"}},\"Property\":\"Status\"}},\"filter\":{\"Version\":2,\"From\":[{\"Name\":\"f\",\"Entity\":\"factInvoices\",\"Type\":0}],\"Where\":[{\"Condition\":{\"In\":{\"Expressions\":[{\"Column\":{\"Expression\":{\"SourceRef\":{\"Source\":\"f\"}},\"Property\":\"Status\"}}],\"Values\":[[{\"Literal\":{\"Value\":\"'Late'\"}}]]}}}]},\"type\":\"Categorical\",\"howCreated\":1,\"objects\":{},\"ordinal\":1},{\"name\":\"Filtere237e1c408857151c081\",\"expression\":{\"Column\":{\"Expression\":{\"SourceRef\":{\"Entity\":\"factInvoices\"}},\"Property\":\"Origin City\"}},\"type\":\"Categorical\",\"howCreated\":0,\"isHiddenInViewMode\":false,\"ordinal\":2}]",
          "height": 505.64,
          "width": 345.34,
          "x": 889.87,
          "y": 129.65,
          "z": 2000.00
        },
        {
          "config": "{\"name\":\"fe7cd3471532abe50645\",\"layouts\":[{\"id\":0,\"position\":{\"x\":610.5340699815838,\"y\":81.32596685082873,\"z\":10000,\"width\":236.9060773480663,\"height\":48.32412523020258,\"tabOrder\":10000}}],\"singleVisual\":{\"visualType\":\"advancedSlicerVisual\",\"projections\":{\"Values\":[{\"queryRef\":\"factInvoices.Origin Country\"}]},\"prototypeQuery\":{\"Version\":2,\"From\":[{\"Name\":\"f\",\"Entity\":\"factInvoices\",\"Type\":0}],\"Select\":[{\"Column\":{\"Expression\":{\"SourceRef\":{\"Source\":\"f\"}},\"Property\":\"Origin Country\"},\"Name\":\"factInvoices.Origin Country\",\"NativeReferenceName\":\"Origin Country\"}]},\"drillFilterOtherVisuals\":true,\"objects\":{\"layout\":[{\"properties\":{\"orientation\":{\"expr\":{\"Literal\":{\"Value\":\"2D\"}}}}}],\"general\":[{\"properties\":{}}],\"selection\":[{\"properties\":{\"singleSelect\":{\"expr\":{\"Literal\":{\"Value\":\"true\"}}},\"strictSingleSelect\":{\"expr\":{\"Literal\":{\"Value\":\"false\"}}}}}],\"shapeCustomRectangle\":[{\"properties\":{\"tileShape\":{\"expr\":{\"Literal\":{\"Value\":\"'rectangleRoundedByPixel'\"}}},\"rectangleRoundedCurve\":{\"expr\":{\"Literal\":{\"Value\":\"14L\"}}},\"rectangleRoundedCurveCustomStyle\":{\"expr\":{\"Literal\":{\"Value\":\"false\"}}}},\"selector\":{\"id\":\"default\"}}],\"value\":[{\"properties\":{\"show\":{\"expr\":{\"Literal\":{\"Value\":\"true\"}}}}},{\"properties\":{\"horizontalAlignment\":{\"expr\":{\"Literal\":{\"Value\":\"'center'\"}}},\"textWrap\":{\"expr\":{\"Literal\":{\"Value\":\"false\"}}}},\"selector\":{\"id\":\"default\"}},{\"properties\":{\"fontColor\":{\"solid\":{\"color\":{\"expr\":{\"ThemeDataColor\":{\"ColorId\":1,\"Percent\":0}}}}}},\"selector\":{\"data\":[{\"dataViewWildcard\":{\"matchingOption\":1}}],\"id\":\"default\"}}],\"fillCustom\":[{\"properties\":{\"show\":{\"expr\":{\"Literal\":{\"Value\":\"true\"}}}}},{\"properties\":{\"transparency\":{\"expr\":{\"Literal\":{\"Value\":\"100D\"}}}},\"selector\":{\"id\":\"default\"}},{\"properties\":{\"transparency\":{\"expr\":{\"Literal\":{\"Value\":\"26D\"}}}},\"selector\":{\"id\":\"hover\"}},{\"properties\":{\"fillColor\":{\"solid\":{\"color\":{\"expr\":{\"ThemeDataColor\":{\"ColorId\":0,\"Percent\":-0.5}}}}}},\"selector\":{\"data\":[{\"dataViewWildcard\":{\"matchingOption\":1}}],\"id\":\"hover\"}},{\"properties\":{\"fillColor\":{\"solid\":{\"color\":{\"expr\":{\"ThemeDataColor\":{\"ColorId\":3,\"Percent\":0}}}}}},\"selector\":{\"data\":[{\"dataViewWildcard\":{\"matchingOption\":1}}],\"id\":\"press\"}},{\"properties\":{\"transparency\":{\"expr\":{\"Literal\":{\"Value\":\"31D\"}}}},\"selector\":{\"id\":\"press\"}},{\"properties\":{\"fillColor\":{\"solid\":{\"color\":{\"expr\":{\"ThemeDataColor\":{\"ColorId\":5,\"Percent\":0}}}}}},\"selector\":{\"data\":[{\"dataViewWildcard\":{\"matchingOption\":1}}],\"id\":\"selected\"}},{\"properties\":{\"transparency\":{\"expr\":{\"Literal\":{\"Value\":\"28D\"}}}},\"selector\":{\"id\":\"selected\"}}],\"glowCustom\":[{\"properties\":{\"show\":{\"expr\":{\"Literal\":{\"Value\":\"false\"}}}},\"selector\":{\"id\":\"default\"}},{\"properties\":{\"show\":{\"expr\":{\"Literal\":{\"Value\":\"false\"}}}},\"selector\":{\"id\":\"hover\"}},{\"properties\":{\"show\":{\"expr\":{\"Literal\":{\"Value\":\"true\"}}},\"position\":{\"expr\":{\"Literal\":{\"Value\":\"'Inner'\"}}}},\"selector\":{\"id\":\"selected\"}}],\"shadowCustom\":[{\"properties\":{\"show\":{\"expr\":{\"Literal\":{\"Value\":\"false\"}}}},\"selector\":{\"id\":\"hover\"}},{\"properties\":{\"show\":{\"expr\":{\"Literal\":{\"Value\":\"false\"}}}},\"selector\":{\"id\":\"default\"}}],\"outline\":[{\"properties\":{\"show\":{\"expr\":{\"Literal\":{\"Value\":\"true\"}}}},\"selector\":{\"id\":\"default\"}}],\"accentBar\":[{\"properties\":{\"show\":{\"expr\":{\"Literal\":{\"Value\":\"false\"}}}},\"selector\":{\"id\":\"default\"}}],\"padding\":[{\"properties\":{\"paddingSelection\":{\"expr\":{\"Literal\":{\"Value\":\"'Normal'\"}}}},\"selector\":{\"id\":\"selected\"}}]},\"vcObjects\":{\"title\":[{\"properties\":{\"show\":{\"expr\":{\"Literal\":{\"Value\":\"false\"}}}}}],\"background\":[{\"properties\":{\"show\":{\"expr\":{\"Literal\":{\"Value\":\"false\"}}}}}]}}}",
          "filters": "[]",
          "height": 48.32,
          "width": 236.91,
          "x": 610.53,
          "y": 81.33,
          "z": 10000.00
        }
      ],
      "width": 1280.00
    }
  ]
}